bigdatafilter/__init__.py
bigdatafilter/__main__.py
bigdatafilter-0.1.4.dist-info/WHEEL
bigdatafilter-0.1.4.dist-info/METADATA
bigdatafilter-0.1.4.dist-info/RECORD
